db/__init__.py
db/crud.py
db/database.py
db/models.py
sb-bridge-portal/oanda_interact.py
sb-bridge-portal/node_modules/flatted/python/flatted.py
skyblue_bridge/__init__.py
skyblue_bridge/metatrader_client.py
skyblue_bridge-0.2.1.dist-info/METADATA
skyblue_bridge-0.2.1.dist-info/WHEEL
skyblue_bridge-0.2.1.dist-info/top_level.txt
skyblue_bridge-0.2.1.dist-info/RECORD
